README.md
setup.py
autobnn/__init__.py
autobnn/bnn.py
autobnn/bnn_test.py
autobnn/bnn_tree.py
autobnn/bnn_tree_test.py
autobnn/estimators.py
autobnn/estimators_test.py
autobnn/kernels.py
autobnn/kernels_test.py
autobnn/likelihoods.py
autobnn/likelihoods_test.py
autobnn/models.py
autobnn/models_test.py
autobnn/operators.py
autobnn/operators_test.py
autobnn/training_util.py
autobnn/training_util_test.py
autobnn/util.py
autobnn/util_test.py
autobnn/version.py
autobnn.egg-info/PKG-INFO
autobnn.egg-info/SOURCES.txt
autobnn.egg-info/dependency_links.txt
autobnn.egg-info/not-zip-safe
autobnn.egg-info/requires.txt
autobnn.egg-info/top_level.txt