Metadata-Version: 2.1
Name: autobnn
Version: 0.0.2.dev0
Summary: Package for training Gaussian process-like Bayesian Neural Networks with composite structure.
Home-page: https://github.com/tensorflow/probability/tree/main/spinoffs/autobnn
Author: Google LLC
Author-email: no-reply@google.com
License: Apache 2.0
Keywords: tensorflow jax probability statistics bayesian machine learning
Classifier: Development Status :: 4 - Beta
Classifier: Intended Audience :: Developers
Classifier: Intended Audience :: Education
Classifier: Intended Audience :: Science/Research
Classifier: License :: OSI Approved :: Apache Software License
Classifier: Programming Language :: Python :: 3
Classifier: Topic :: Scientific/Engineering
Classifier: Topic :: Scientific/Engineering :: Mathematics
Classifier: Topic :: Scientific/Engineering :: Artificial Intelligence
Classifier: Topic :: Software Development
Classifier: Topic :: Software Development :: Libraries
Classifier: Topic :: Software Development :: Libraries :: Python Modules
Requires-Python: >=3.6
